rctf/__init__.py
rctf/config.py
rctf/logger.py
rctf/rctf.py
rctf-cli/rctf/__init__.py
rctf-cli/rctf/config.py
rctf-cli/rctf/logger.py
rctf-cli/rctf/rctf.py
rctf_cli-1.0.data/scripts/rctf
rctf_cli-1.0.data/scripts/rctf.sh
rctf_cli-1.0.dist-info/LICENSE
rctf_cli-1.0.dist-info/METADATA
rctf_cli-1.0.dist-info/WHEEL
rctf_cli-1.0.dist-info/top_level.txt
rctf_cli-1.0.dist-info/RECORD
